wtftortoise/__init__.py
wtftortoise/orm.py
wtf_tortoise-0.0.4.dist-info/LICENSE
wtf_tortoise-0.0.4.dist-info/METADATA
wtf_tortoise-0.0.4.dist-info/WHEEL
wtf_tortoise-0.0.4.dist-info/top_level.txt
wtf_tortoise-0.0.4.dist-info/RECORD
