Metadata-Version: 2.1
Name: wtf-tortoise
Version: 0.0.4
Summary: Implementation of WTForms for Tortoise ORM
Home-page: https://github.com/fsecada01/wtf-tortoise
Author: sinisaos (packaged by fsecada01
Author-email: francis.secada@gmail.com
License: UNKNOWN
Project-URL: Bug Tracker, https://github.com/fsecada01/wtf-tortoise/issues
Platform: UNKNOWN
Classifier: Programming Language :: Python :: 3
Classifier: License :: OSI Approved :: MIT License
Classifier: Operating System :: OS Independent
Requires-Python: >=3.7
License-File: LICENSE
Requires-Dist: tortoise-orm
Requires-Dist: uvicorn
Requires-Dist: wtforms
Requires-Dist: wtforms[email]
